hacking_shield/__init__.py
hacking_shield/client.py
hacking_shield-0.2.3.dist-info/LICENSE
hacking_shield-0.2.3.dist-info/METADATA
hacking_shield-0.2.3.dist-info/WHEEL
hacking_shield-0.2.3.dist-info/top_level.txt
hacking_shield-0.2.3.dist-info/RECORD
