Metadata-Version: 2.1
Name: hacking-shield
Version: 0.2.3
Summary: Client for detecting harmful SQL queries using a third-party API
Home-page: https://github.com/kondwani0099/hacking-shield
Author: Kondwani Nyirenda
Author-email: kondwaninyirenda99@gmail.com
Classifier: Programming Language :: Python :: 3
Classifier: License :: OSI Approved :: MIT License
Classifier: Operating System :: OS Independent
Requires-Python: >=3.6
License-File: LICENSE
Requires-Dist: requests >=2.0.0
